<?xml version="1.0" encoding="utf-8" ?>
<dwsync>
<file name="index.html" server="bitlamp.wctc.edu/public_html/php2/" local="130939081600000000" remote="130939081600000000" Dst="1" />
<file name="examples.html" server="bitlamp.wctc.edu/public_html/php2/" local="130939081700000000" remote="130939081700000000" Dst="1" />
<file name="configuration.html" server="bitlamp.wctc.edu/public_html/php2/" local="130939081630000000" remote="130939081630000000" Dst="1" />
<file name="connecting.html" server="bitlamp.wctc.edu/public_html/php2/" local="130939081580000000" remote="130939081580000000" Dst="1" />
<file name="queries.html" server="bitlamp.wctc.edu/public_html/php2/" local="130939081550000000" remote="130939081550000000" Dst="1" />
<file name="results.html" server="bitlamp.wctc.edu/public_html/php2/" local="130939081490000000" remote="130939081490000000" Dst="1" />
<file name="helpers.html" server="bitlamp.wctc.edu/public_html/php2/" local="130939081590000000" remote="130939081590000000" Dst="1" />
<file name="query_builder.html" server="bitlamp.wctc.edu/public_html/php2/" local="130939081680000000" remote="130939081680000000" Dst="1" />
<file name="transactions.html" server="bitlamp.wctc.edu/public_html/php2/" local="130939081540000000" remote="130939081540000000" Dst="1" />
<file name="metadata.html" server="bitlamp.wctc.edu/public_html/php2/" local="130939081650000000" remote="130939081650000000" Dst="1" />
<file name="call_function.html" server="bitlamp.wctc.edu/public_html/php2/" local="130939081610000000" remote="130939081610000000" Dst="1" />
<file name="caching.html" server="bitlamp.wctc.edu/public_html/php2/" local="130939081640000000" remote="130939081640000000" Dst="1" />
<file name="forge.html" server="bitlamp.wctc.edu/public_html/php2/" local="130939081510000000" remote="130939081510000000" Dst="1" />
<file name="utilities.html" server="bitlamp.wctc.edu/public_html/php2/" local="130939081570000000" remote="130939081570000000" Dst="1" />
<file name="db_driver_reference.html" server="bitlamp.wctc.edu/public_html/php2/" local="130939081530000000" remote="130939081530000000" Dst="1" />
</dwsync>